{"firstCanPrevDropdownKEEP": "Temporal trace of candidate cluster", "LineEdit#CumulativeSum.CumulativeSum#show_fits#None": "True", "LineEdit#CumulativeSum.CumulativeSum#show_first#None": "False", "LineEdit#CumulativeSum.CumulativeSum#weigh_first#None": "False", "LineEdit#CumulativeSum.CumulativeSum#use_background_parameters#None": "True", "LineEdit#OneDProjection.OneDProjection#t_bin_width#None": "1", "LineEdit#OneDProjection.OneDProjection#show_first#None": "False", "LineEdit#OneDProjection.OneDProjection#weigh_first#None": "False", "secondCanPrevDropdownKEEP": "2D projections of candidate cluster", "LineEdit#TwoDProjections.TwoDProjection#t_bin_width#None": "10", "LineEdit#TwoDProjections.TwoDProjection#xy_bin_width#None": "1", "qt_spinbox_lineedit": "10", "slice_label": "0", "axis_label": "0", "playDirectionCheckBox": false, "VisualisationDropdownKEEP": "Gaussian-blurred with fixed sigma", "LineEdit#Gaussian_display.GaussianKernel_fixedSigma#px_size#None": "10", "LineEdit#Gaussian_display.GaussianKernel_fixedSigma#sigma#None": "9.2", "PostProcessingDropdownKEEP": "Load stored drift correction DME/RCC", "LineEdit#DriftCorr_DME.Load_storedData#fileLoc#None": "//ifmb-nas/AG Endesfelder/Data/Koen/Scientific/EBS_data/3d.csvdriftcorr.npz", "processing_dataLocationInput": "C:/Users/Koen Martens/sciebo - Martens, Koen (kmartens@uni-bonn.de)@uni-bonn.sciebo.de (2)/Data/Ecoli/Ecoli_RpoC_Full_xyCut.hdf5", "selectPolarityOptions_dropdown": "Pos and neg seperately", "run_startTLineEdit": "0", "run_durationTLineEdit": "inf", "run_minXLineEdit": "0", "run_maxXLineEdit": "inf", "run_minYLineEdit": "0", "run_maxYLineEdit": "inf", "CandidateFindingDropdownPos": "Eigen-feature analysis (pos)", "LineEdit#DBSCAN.DBSCAN_onlyHighDensity#distance_radius_lookup#pos": "7", "LineEdit#DBSCAN.DBSCAN_onlyHighDensity#density_multiplier#pos": "1.5", "LineEdit#DBSCAN.DBSCAN_onlyHighDensity#min_cluster_size#pos": "17", "LineEdit#DBSCAN.DBSCAN_onlyHighDensity#ratio_ms_to_px#pos": "35.0", "LineEdit#DBSCAN.DBSCAN_onlyHighDensity#DBSCAN_eps#pos": "6", "LineEdit#DBSCAN.DBSCAN_onlyHighDensity#min_consec#pos": "1", "LineEdit#DBSCAN.DBSCAN_allEvents#distance_radius_lookup#pos": "7", "LineEdit#DBSCAN.DBSCAN_allEvents#density_multiplier#pos": "1.5", "LineEdit#DBSCAN.DBSCAN_allEvents#min_cluster_size#pos": "17", "LineEdit#DBSCAN.DBSCAN_allEvents#ratio_ms_to_px#pos": "35.0", "LineEdit#DBSCAN.DBSCAN_allEvents#DBSCAN_eps#pos": "6", "LineEdit#DBSCAN.DBSCAN_allEvents#padding_xy#pos": "0", "LineEdit#DBSCAN.DBSCAN_allEvents#min_consec#pos": "1", "LineEdit#DBSCAN.DBSCAN_allEvents_remove_outliers#distance_radius_lookup#pos": "7", "LineEdit#DBSCAN.DBSCAN_allEvents_remove_outliers#density_multiplier#pos": "1.5", "LineEdit#DBSCAN.DBSCAN_allEvents_remove_outliers#min_cluster_size#pos": "17", "LineEdit#DBSCAN.DBSCAN_allEvents_remove_outliers#ratio_ms_to_px#pos": "35.0", "LineEdit#DBSCAN.DBSCAN_allEvents_remove_outliers#DBSCAN_eps#pos": "3", "LineEdit#DBSCAN.DBSCAN_allEvents_remove_outliers#padding_xy#pos": "2", "LineEdit#DBSCAN.DBSCAN_allEvents_remove_outliers#outlier_removal_radius#pos": "3", "LineEdit#DBSCAN.DBSCAN_allEvents_remove_outliers#outlier_removal_nbPoints#pos": "30", "LineEdit#DBSCAN.DBSCAN_allEvents_remove_outliers#min_consec#pos": "1", "LineEdit#EigenFeatureAnalysis.eigenFeature_analysis#search_n_neighbours#pos": "50", "LineEdit#EigenFeatureAnalysis.eigenFeature_analysis#max_eigenval_cutoff#pos": "45", "LineEdit#EigenFeatureAnalysis.eigenFeature_analysis#linearity_cutoff#pos": "0.7", "LineEdit#EigenFeatureAnalysis.eigenFeature_analysis#ratio_ms_to_px#pos": "40", "LineEdit#EigenFeatureAnalysis.eigenFeature_analysis#DBSCAN_eps#pos": "4", "LineEdit#EigenFeatureAnalysis.eigenFeature_analysis#DBSCAN_n_neighbours#pos": "5", "LineEdit#EigenFeatureAnalysis.eigenFeature_analysis#debug#pos": "False", "LineEdit#EigenFeatureAnalysis.eigen_feature_analysis_autoRadiusSelect#max_eigenval_cutoff#pos": "0.0", "LineEdit#EigenFeatureAnalysis.eigen_feature_analysis_autoRadiusSelect#linearity_cutoff#pos": "0.6", "LineEdit#EigenFeatureAnalysis.eigen_feature_analysis_autoRadiusSelect#min_radius#pos": "4", "LineEdit#EigenFeatureAnalysis.eigen_feature_analysis_autoRadiusSelect#max_radius#pos": "10", "LineEdit#EigenFeatureAnalysis.eigen_feature_analysis_autoRadiusSelect#ratio_ms_to_px#pos": "35.0", "LineEdit#EigenFeatureAnalysis.eigen_feature_analysis_autoRadiusSelect#DBSCAN_eps#pos": "3", "LineEdit#EigenFeatureAnalysis.eigen_feature_analysis_autoRadiusSelect#DBSCAN_n_neighbours#pos": "17", "LineEdit#EigenFeatureAnalysis.eigen_feature_analysis_autoRadiusSelect#debug#pos": "False", "LineEdit#EigenFeatureAnalysis.eigenFeature_analysis_and_bbox_finding#search_n_neighbours#pos": "50", "LineEdit#EigenFeatureAnalysis.eigenFeature_analysis_and_bbox_finding#max_eigenval_cutoff#pos": "0.0", "LineEdit#EigenFeatureAnalysis.eigenFeature_analysis_and_bbox_finding#linearity_cutoff#pos": "0.7", "LineEdit#EigenFeatureAnalysis.eigenFeature_analysis_and_bbox_finding#ratio_ms_to_px#pos": "20.0", "LineEdit#EigenFeatureAnalysis.eigenFeature_analysis_and_bbox_finding#DBSCAN_eps#pos": "3", "LineEdit#EigenFeatureAnalysis.eigenFeature_analysis_and_bbox_finding#DBSCAN_n_neighbours#pos": "20", "LineEdit#EigenFeatureAnalysis.eigenFeature_analysis_and_bbox_finding#bbox_padding#pos": "4", "LineEdit#EigenFeatureAnalysis.eigenFeature_analysis_and_bbox_finding#debug#pos": "False", "LineEdit#FrameBasedFinding.FrameBased_finding#threshold_detection#pos": "3.0", "LineEdit#FrameBasedFinding.FrameBased_finding#exclusion_radius#pos": "4.0", "LineEdit#FrameBasedFinding.FrameBased_finding#min_diameter#pos": "1.25", "LineEdit#FrameBasedFinding.FrameBased_finding#max_diameter#pos": "4.0", "LineEdit#FrameBasedFinding.FrameBased_finding#frame_time#pos": "100.0", "LineEdit#FrameBasedFinding.FrameBased_finding#candidate_radius#pos": "4.0", "LineEdit#FrameBasedFinding.FrameBased_finding#multithread#pos": "True", "LineEdit#LoadExistingFinding.LoadExistingFinding#File_Location#pos": "C:/Data/EBS/LogvsNormalvsMean/20240222_DNAPAINT_xyCut._FindingResults_PosOnly_20240522_165043_LogGauss.pickle", "CandidateFindingDropdownNeg": "Eigen-feature analysis (neg)", "LineEdit#DBSCAN.DBSCAN_onlyHighDensity#distance_radius_lookup#neg": "7", "LineEdit#DBSCAN.DBSCAN_onlyHighDensity#density_multiplier#neg": "1.5", "LineEdit#DBSCAN.DBSCAN_onlyHighDensity#min_cluster_size#neg": "17", "LineEdit#DBSCAN.DBSCAN_onlyHighDensity#ratio_ms_to_px#neg": "35.0", "LineEdit#DBSCAN.DBSCAN_onlyHighDensity#DBSCAN_eps#neg": "6", "LineEdit#DBSCAN.DBSCAN_onlyHighDensity#min_consec#neg": "1", "LineEdit#DBSCAN.DBSCAN_allEvents#distance_radius_lookup#neg": "7", "LineEdit#DBSCAN.DBSCAN_allEvents#density_multiplier#neg": "1.5", "LineEdit#DBSCAN.DBSCAN_allEvents#min_cluster_size#neg": "17", "LineEdit#DBSCAN.DBSCAN_allEvents#ratio_ms_to_px#neg": "35.0", "LineEdit#DBSCAN.DBSCAN_allEvents#DBSCAN_eps#neg": "6", "LineEdit#DBSCAN.DBSCAN_allEvents#padding_xy#neg": "0", "LineEdit#DBSCAN.DBSCAN_allEvents#min_consec#neg": "1", "LineEdit#DBSCAN.DBSCAN_allEvents_remove_outliers#distance_radius_lookup#neg": "7", "LineEdit#DBSCAN.DBSCAN_allEvents_remove_outliers#density_multiplier#neg": "1.5", "LineEdit#DBSCAN.DBSCAN_allEvents_remove_outliers#min_cluster_size#neg": "17", "LineEdit#DBSCAN.DBSCAN_allEvents_remove_outliers#ratio_ms_to_px#neg": "35.0", "LineEdit#DBSCAN.DBSCAN_allEvents_remove_outliers#DBSCAN_eps#neg": "3", "LineEdit#DBSCAN.DBSCAN_allEvents_remove_outliers#padding_xy#neg": "2", "LineEdit#DBSCAN.DBSCAN_allEvents_remove_outliers#outlier_removal_radius#neg": "3", "LineEdit#DBSCAN.DBSCAN_allEvents_remove_outliers#outlier_removal_nbPoints#neg": "30", "LineEdit#DBSCAN.DBSCAN_allEvents_remove_outliers#min_consec#neg": "1", "LineEdit#EigenFeatureAnalysis.eigenFeature_analysis#search_n_neighbours#neg": "50", "LineEdit#EigenFeatureAnalysis.eigenFeature_analysis#max_eigenval_cutoff#neg": "75", "LineEdit#EigenFeatureAnalysis.eigenFeature_analysis#linearity_cutoff#neg": "0.7", "LineEdit#EigenFeatureAnalysis.eigenFeature_analysis#ratio_ms_to_px#neg": "40", "LineEdit#EigenFeatureAnalysis.eigenFeature_analysis#DBSCAN_eps#neg": "4", "LineEdit#EigenFeatureAnalysis.eigenFeature_analysis#DBSCAN_n_neighbours#neg": "5", "LineEdit#EigenFeatureAnalysis.eigenFeature_analysis#debug#neg": "False", "LineEdit#EigenFeatureAnalysis.eigen_feature_analysis_autoRadiusSelect#max_eigenval_cutoff#neg": "0.0", "LineEdit#EigenFeatureAnalysis.eigen_feature_analysis_autoRadiusSelect#linearity_cutoff#neg": "0.6", "LineEdit#EigenFeatureAnalysis.eigen_feature_analysis_autoRadiusSelect#min_radius#neg": "4", "LineEdit#EigenFeatureAnalysis.eigen_feature_analysis_autoRadiusSelect#max_radius#neg": "10", "LineEdit#EigenFeatureAnalysis.eigen_feature_analysis_autoRadiusSelect#ratio_ms_to_px#neg": "35.0", "LineEdit#EigenFeatureAnalysis.eigen_feature_analysis_autoRadiusSelect#DBSCAN_eps#neg": "3", "LineEdit#EigenFeatureAnalysis.eigen_feature_analysis_autoRadiusSelect#DBSCAN_n_neighbours#neg": "17", "LineEdit#EigenFeatureAnalysis.eigen_feature_analysis_autoRadiusSelect#debug#neg": "False", "LineEdit#EigenFeatureAnalysis.eigenFeature_analysis_and_bbox_finding#search_n_neighbours#neg": "50", "LineEdit#EigenFeatureAnalysis.eigenFeature_analysis_and_bbox_finding#max_eigenval_cutoff#neg": "0.0", "LineEdit#EigenFeatureAnalysis.eigenFeature_analysis_and_bbox_finding#linearity_cutoff#neg": "0.7", "LineEdit#EigenFeatureAnalysis.eigenFeature_analysis_and_bbox_finding#ratio_ms_to_px#neg": "20.0", "LineEdit#EigenFeatureAnalysis.eigenFeature_analysis_and_bbox_finding#DBSCAN_eps#neg": "3", "LineEdit#EigenFeatureAnalysis.eigenFeature_analysis_and_bbox_finding#DBSCAN_n_neighbours#neg": "20", "LineEdit#EigenFeatureAnalysis.eigenFeature_analysis_and_bbox_finding#bbox_padding#neg": "1", "LineEdit#EigenFeatureAnalysis.eigenFeature_analysis_and_bbox_finding#debug#neg": "False", "LineEdit#FrameBasedFinding.FrameBased_finding#threshold_detection#neg": "3.0", "LineEdit#FrameBasedFinding.FrameBased_finding#exclusion_radius#neg": "4.0", "LineEdit#FrameBasedFinding.FrameBased_finding#min_diameter#neg": "1.25", "LineEdit#FrameBasedFinding.FrameBased_finding#max_diameter#neg": "4.0", "LineEdit#FrameBasedFinding.FrameBased_finding#frame_time#neg": "100.0", "LineEdit#FrameBasedFinding.FrameBased_finding#candidate_radius#neg": "4.0", "LineEdit#FrameBasedFinding.FrameBased_finding#multithread#neg": "True", "LineEdit#LoadExistingFinding.LoadExistingFinding#File_Location#neg": "C:/Data/EBS/LogvsNormalvsMean/20240222_DNAPAINT_xyCut._FindingResults_NegOnly_20240522_165043_LogGauss.pickle", "CandidateFindingDropdownMix": "Eigen-feature analysis (mix)", "LineEdit#DBSCAN.DBSCAN_onlyHighDensity#distance_radius_lookup#mix": "7", "LineEdit#DBSCAN.DBSCAN_onlyHighDensity#density_multiplier#mix": "1.5", "LineEdit#DBSCAN.DBSCAN_onlyHighDensity#min_cluster_size#mix": "17", "LineEdit#DBSCAN.DBSCAN_onlyHighDensity#ratio_ms_to_px#mix": "35.0", "LineEdit#DBSCAN.DBSCAN_onlyHighDensity#DBSCAN_eps#mix": "6", "LineEdit#DBSCAN.DBSCAN_onlyHighDensity#min_consec#mix": "1", "LineEdit#DBSCAN.DBSCAN_allEvents#distance_radius_lookup#mix": "7", "LineEdit#DBSCAN.DBSCAN_allEvents#density_multiplier#mix": "1.5", "LineEdit#DBSCAN.DBSCAN_allEvents#min_cluster_size#mix": "17", "LineEdit#DBSCAN.DBSCAN_allEvents#ratio_ms_to_px#mix": "35.0", "LineEdit#DBSCAN.DBSCAN_allEvents#DBSCAN_eps#mix": "6", "LineEdit#DBSCAN.DBSCAN_allEvents#padding_xy#mix": "0", "LineEdit#DBSCAN.DBSCAN_allEvents#min_consec#mix": "1", "LineEdit#DBSCAN.DBSCAN_allEvents_remove_outliers#distance_radius_lookup#mix": "7", "LineEdit#DBSCAN.DBSCAN_allEvents_remove_outliers#density_multiplier#mix": "1.5", "LineEdit#DBSCAN.DBSCAN_allEvents_remove_outliers#min_cluster_size#mix": "17", "LineEdit#DBSCAN.DBSCAN_allEvents_remove_outliers#ratio_ms_to_px#mix": "35.0", "LineEdit#DBSCAN.DBSCAN_allEvents_remove_outliers#DBSCAN_eps#mix": "3", "LineEdit#DBSCAN.DBSCAN_allEvents_remove_outliers#padding_xy#mix": "2", "LineEdit#DBSCAN.DBSCAN_allEvents_remove_outliers#outlier_removal_radius#mix": "3", "LineEdit#DBSCAN.DBSCAN_allEvents_remove_outliers#outlier_removal_nbPoints#mix": "30", "LineEdit#DBSCAN.DBSCAN_allEvents_remove_outliers#min_consec#mix": "1", "LineEdit#EigenFeatureAnalysis.eigenFeature_analysis#search_n_neighbours#mix": "50", "LineEdit#EigenFeatureAnalysis.eigenFeature_analysis#max_eigenval_cutoff#mix": "20", "LineEdit#EigenFeatureAnalysis.eigenFeature_analysis#linearity_cutoff#mix": "0.7", "LineEdit#EigenFeatureAnalysis.eigenFeature_analysis#ratio_ms_to_px#mix": "10", "LineEdit#EigenFeatureAnalysis.eigenFeature_analysis#DBSCAN_eps#mix": "4", "LineEdit#EigenFeatureAnalysis.eigenFeature_analysis#DBSCAN_n_neighbours#mix": "10", "LineEdit#EigenFeatureAnalysis.eigenFeature_analysis#debug#mix": "False", "LineEdit#EigenFeatureAnalysis.eigen_feature_analysis_autoRadiusSelect#max_eigenval_cutoff#mix": "0.0", "LineEdit#EigenFeatureAnalysis.eigen_feature_analysis_autoRadiusSelect#linearity_cutoff#mix": "0.6", "LineEdit#EigenFeatureAnalysis.eigen_feature_analysis_autoRadiusSelect#min_radius#mix": "4", "LineEdit#EigenFeatureAnalysis.eigen_feature_analysis_autoRadiusSelect#max_radius#mix": "10", "LineEdit#EigenFeatureAnalysis.eigen_feature_analysis_autoRadiusSelect#ratio_ms_to_px#mix": "35.0", "LineEdit#EigenFeatureAnalysis.eigen_feature_analysis_autoRadiusSelect#DBSCAN_eps#mix": "3", "LineEdit#EigenFeatureAnalysis.eigen_feature_analysis_autoRadiusSelect#DBSCAN_n_neighbours#mix": "17", "LineEdit#EigenFeatureAnalysis.eigen_feature_analysis_autoRadiusSelect#debug#mix": "False", "LineEdit#EigenFeatureAnalysis.eigenFeature_analysis_and_bbox_finding#search_n_neighbours#mix": "50", "LineEdit#EigenFeatureAnalysis.eigenFeature_analysis_and_bbox_finding#max_eigenval_cutoff#mix": "0.0", "LineEdit#EigenFeatureAnalysis.eigenFeature_analysis_and_bbox_finding#linearity_cutoff#mix": "0.7", "LineEdit#EigenFeatureAnalysis.eigenFeature_analysis_and_bbox_finding#ratio_ms_to_px#mix": "20.0", "LineEdit#EigenFeatureAnalysis.eigenFeature_analysis_and_bbox_finding#DBSCAN_eps#mix": "3", "LineEdit#EigenFeatureAnalysis.eigenFeature_analysis_and_bbox_finding#DBSCAN_n_neighbours#mix": "20", "LineEdit#EigenFeatureAnalysis.eigenFeature_analysis_and_bbox_finding#bbox_padding#mix": "1", "LineEdit#EigenFeatureAnalysis.eigenFeature_analysis_and_bbox_finding#debug#mix": "False", "LineEdit#FrameBasedFinding.FrameBased_finding#threshold_detection#mix": "3.0", "LineEdit#FrameBasedFinding.FrameBased_finding#exclusion_radius#mix": "4.0", "LineEdit#FrameBasedFinding.FrameBased_finding#min_diameter#mix": "1.25", "LineEdit#FrameBasedFinding.FrameBased_finding#max_diameter#mix": "4.0", "LineEdit#FrameBasedFinding.FrameBased_finding#frame_time#mix": "100.0", "LineEdit#FrameBasedFinding.FrameBased_finding#candidate_radius#mix": "4.0", "LineEdit#FrameBasedFinding.FrameBased_finding#multithread#mix": "True", "LineEdit#LoadExistingFinding.LoadExistingFinding#File_Location#mix": "", "CandidateFittingDropdownPos": "2D LogGaussian (pos)", "ComboBox#GaussianFitting.Gaussian2D#time_kwarg#pos": "Lognormal CDF (first events, weighted)", "ComboBox#GaussianFitting.Gaussian2D#dist_kwarg#pos": "2D histogram of x, y positions", "LineEdit#GaussianFitting.Gaussian2D#expected_width#pos": "150.0", "LineEdit#GaussianFitting.Gaussian2D#fitting_tolerance#pos": "1.0", "ComboBox#GaussianFitting.LogGaussian2D#time_kwarg#pos": "Lognormal CDF (first events, weighted)", "ComboBox#GaussianFitting.LogGaussian2D#dist_kwarg#pos": "2D histogram of x, y positions", "LineEdit#GaussianFitting.LogGaussian2D#expected_width#pos": "150.0", "LineEdit#GaussianFitting.LogGaussian2D#fitting_tolerance#pos": "4", "ComboBox#GaussianFitting.Gaussian3D#time_kwarg#pos": "Lognormal CDF (first events, weighted)", "ComboBox#GaussianFitting.Gaussian3D#dist_kwarg#pos": "2D histogram of x, y positions", "LineEdit#GaussianFitting.Gaussian3D#theta#pos": "0", "LineEdit#GaussianFitting.Gaussian3D#expected_width#pos": "150.0", "LineEdit#GaussianFitting.Gaussian3D#fitting_tolerance#pos": "1.0", "LineEdit#GaussianFitting.Gaussian3D#calibration_file#pos": "", "LineEdit#LoadExistingFitting.LoadExistingFitting#File_Location#pos": "C:/Data/EBS/LogvsNormalvsMean/20240222_DNAPAINT_xyCut._FittingResults_PosOnly_20240522_165043_LogGauss.pickle", "ComboBox#PhasorFitting.PhasorFitting#dist_kwarg#pos": "2D histogram of x, y positions", "ComboBox#PhasorFitting.PhasorFitting_customTimeFit#time_kwarg#pos": "Lognormal CDF (first events, weighted)", "ComboBox#PhasorFitting.PhasorFitting_customTimeFit#dist_kwarg#pos": "2D histogram of x, y positions", "ComboBox#Radial_Symmetry.RadialSym2D#time_kwarg#pos": "Lognormal CDF (first events, weighted)", "LineEdit#Radial_Symmetry.RadialSym3D#time_bin_width#pos": "10.0", "ComboBox#SimpleOperants.AverageXYpos#time_kwarg#pos": "Lognormal CDF (first events, weighted)", "LineEdit#UnivariateSplineFitting.Spline1D#smoothing_factor#pos": "0.07", "LineEdit#UnivariateSplineFitting.Spline1D#localization_sampling#pos": "10.0", "LineEdit#UnivariateSplineFitting.Spline1D#degree#pos": "3", "CandidateFittingDropdownNeg": "2D LogGaussian (neg)", "ComboBox#GaussianFitting.Gaussian2D#time_kwarg#neg": "Lognormal CDF (first events, weighted)", "ComboBox#GaussianFitting.Gaussian2D#dist_kwarg#neg": "2D histogram of x, y positions", "LineEdit#GaussianFitting.Gaussian2D#expected_width#neg": "150.0", "LineEdit#GaussianFitting.Gaussian2D#fitting_tolerance#neg": "1.0", "ComboBox#GaussianFitting.LogGaussian2D#time_kwarg#neg": "Lognormal CDF (first events, weighted)", "ComboBox#GaussianFitting.LogGaussian2D#dist_kwarg#neg": "2D histogram of x, y positions", "LineEdit#GaussianFitting.LogGaussian2D#expected_width#neg": "150.0", "LineEdit#GaussianFitting.LogGaussian2D#fitting_tolerance#neg": "4", "ComboBox#GaussianFitting.Gaussian3D#time_kwarg#neg": "Lognormal CDF (first events, weighted)", "ComboBox#GaussianFitting.Gaussian3D#dist_kwarg#neg": "2D histogram of x, y positions", "LineEdit#GaussianFitting.Gaussian3D#theta#neg": "0", "LineEdit#GaussianFitting.Gaussian3D#expected_width#neg": "150.0", "LineEdit#GaussianFitting.Gaussian3D#fitting_tolerance#neg": "1.0", "LineEdit#GaussianFitting.Gaussian3D#calibration_file#neg": "", "LineEdit#LoadExistingFitting.LoadExistingFitting#File_Location#neg": "C:/Data/EBS/LogvsNormalvsMean/20240222_DNAPAINT_xyCut._FittingResults_NegOnly_20240522_165043_LogGauss.pickle", "ComboBox#PhasorFitting.PhasorFitting#dist_kwarg#neg": "2D histogram of x, y positions", "ComboBox#PhasorFitting.PhasorFitting_customTimeFit#time_kwarg#neg": "Lognormal CDF (first events, weighted)", "ComboBox#PhasorFitting.PhasorFitting_customTimeFit#dist_kwarg#neg": "2D histogram of x, y positions", "ComboBox#Radial_Symmetry.RadialSym2D#time_kwarg#neg": "Lognormal CDF (first events, weighted)", "LineEdit#Radial_Symmetry.RadialSym3D#time_bin_width#neg": "10.0", "ComboBox#SimpleOperants.AverageXYpos#time_kwarg#neg": "Lognormal CDF (first events, weighted)", "LineEdit#UnivariateSplineFitting.Spline1D#smoothing_factor#neg": "0.07", "LineEdit#UnivariateSplineFitting.Spline1D#localization_sampling#neg": "10.0", "LineEdit#UnivariateSplineFitting.Spline1D#degree#neg": "3", "CandidateFittingDropdownMix": "2D Gaussian (mix)", "ComboBox#GaussianFitting.Gaussian2D#time_kwarg#mix": "Lognormal CDF (first events, weighted)", "ComboBox#GaussianFitting.Gaussian2D#dist_kwarg#mix": "2D histogram of x, y positions", "LineEdit#GaussianFitting.Gaussian2D#expected_width#mix": "150.0", "LineEdit#GaussianFitting.Gaussian2D#fitting_tolerance#mix": "1.0", "ComboBox#GaussianFitting.LogGaussian2D#time_kwarg#mix": "Lognormal CDF (first events, weighted)", "ComboBox#GaussianFitting.LogGaussian2D#dist_kwarg#mix": "2D histogram of x, y positions", "LineEdit#GaussianFitting.LogGaussian2D#expected_width#mix": "150.0", "LineEdit#GaussianFitting.LogGaussian2D#fitting_tolerance#mix": "1.0", "ComboBox#GaussianFitting.Gaussian3D#time_kwarg#mix": "Lognormal CDF (first events, weighted)", "ComboBox#GaussianFitting.Gaussian3D#dist_kwarg#mix": "2D histogram of x, y positions", "LineEdit#GaussianFitting.Gaussian3D#theta#mix": "0", "LineEdit#GaussianFitting.Gaussian3D#expected_width#mix": "150.0", "LineEdit#GaussianFitting.Gaussian3D#fitting_tolerance#mix": "1.0", "LineEdit#GaussianFitting.Gaussian3D#calibration_file#mix": "", "LineEdit#LoadExistingFitting.LoadExistingFitting#File_Location#mix": "", "ComboBox#PhasorFitting.PhasorFitting#dist_kwarg#mix": "2D histogram of x, y positions", "ComboBox#PhasorFitting.PhasorFitting_customTimeFit#time_kwarg#mix": "Lognormal CDF (first events, weighted)", "ComboBox#PhasorFitting.PhasorFitting_customTimeFit#dist_kwarg#mix": "2D histogram of x, y positions", "ComboBox#Radial_Symmetry.RadialSym2D#time_kwarg#mix": "Lognormal CDF (first events, weighted)", "LineEdit#Radial_Symmetry.RadialSym3D#time_bin_width#mix": "10.0", "ComboBox#SimpleOperants.AverageXYpos#time_kwarg#mix": "Lognormal CDF (first events, weighted)", "LineEdit#UnivariateSplineFitting.Spline1D#smoothing_factor#mix": "0.07", "LineEdit#UnivariateSplineFitting.Spline1D#localization_sampling#mix": "10.0", "LineEdit#UnivariateSplineFitting.Spline1D#degree#mix": "3", "preview_startTLineEdit": "0", "preview_durationTLineEdit": "1000", "preview_displayFrameTime": "100", "preview_eventType": "Positive only", "preview_minXLineEdit": "0", "preview_maxXLineEdit": "inf", "preview_minYLineEdit": "0", "preview_maxYLineEdit": "inf"}